fontes_clp/__init__.py
fontes_clp/common/__init__.py
fontes_clp/common/estados.py
fontes_clp/common/sexo.py
fontes_clp/ibge/__init__.py
fontes_clp/ibge/populacao.py
fontes_clp/ibge/dados/dados.xlsx
fontes_clp/sidra/__init__.py
fontes_clp/sidra/sidra.py
fontes_clp/sidra/tabelas.py
fontes_clp/sidra/variaveis.py
fontes_clp/tabnet/__init__.py
fontes_clp/tabnet/grupos.py
fontes_clp/tabnet/morbidade.py
fontes_clp/tabnet/obitos.py
fontes_clp-0.2.3.dist-info/licenses/LICENSE
fontes_clp-0.2.3.dist-info/METADATA
fontes_clp-0.2.3.dist-info/WHEEL
fontes_clp-0.2.3.dist-info/top_level.txt
fontes_clp-0.2.3.dist-info/RECORD
