Metadata-Version: 2.4
Name: fontes_clp
Version: 0.2.3
Summary: Pacote com maneiras simplificadas de extrair dados das fontes do CLP
Requires-Python: >=3.13
License-File: LICENSE
Requires-Dist: beautifulsoup4>=4.13.5
Requires-Dist: httpx>=0.28.1
Requires-Dist: openpyxl>=3.1.5
Requires-Dist: pandas>=2.3.2
Dynamic: license-file
